coininfo_nomisreual/__init__.py
coininfo_nomisreual/info.py
coininfo_nomisreual-0.1.1.dist-info/METADATA
coininfo_nomisreual-0.1.1.dist-info/WHEEL
coininfo_nomisreual-0.1.1.dist-info/top_level.txt
coininfo_nomisreual-0.1.1.dist-info/RECORD
